mcp_server_sdlxliff/__init__.py
mcp_server_sdlxliff/__main__.py
mcp_server_sdlxliff/cache.py
mcp_server_sdlxliff/constants.py
mcp_server_sdlxliff/io.py
mcp_server_sdlxliff/parser.py
mcp_server_sdlxliff/qa.py
mcp_server_sdlxliff/server.py
mcp_server_sdlxliff/tags.py
mcp_server_sdlxliff-1.1.0.dist-info/METADATA
mcp_server_sdlxliff-1.1.0.dist-info/WHEEL
mcp_server_sdlxliff-1.1.0.dist-info/entry_points.txt
mcp_server_sdlxliff-1.1.0.dist-info/licenses/LICENSE
mcp_server_sdlxliff-1.1.0.dist-info/RECORD
