Metadata-Version: 2.4
Name: mcp-server-sdlxliff
Version: 1.1.0
Summary: MCP server for parsing, reading, and modifying SDLXLIFF translation files (SDL Trados Studio format)
Project-URL: Homepage, https://github.com/EugeneAnt/mcp-server-sdlxliff
Project-URL: Repository, https://github.com/EugeneAnt/mcp-server-sdlxliff
Project-URL: Issues, https://github.com/EugeneAnt/mcp-server-sdlxliff/issues
Author: Yevgeni Antonov
License: MIT
License-File: LICENSE
Keywords: cat-tools,localization,mcp,model-context-protocol,sdl-trados,sdlxliff,translation,xliff
Classifier: Development Status :: 4 - Beta
Classifier: Intended Audience :: Developers
Classifier: License :: OSI Approved :: MIT License
Classifier: Programming Language :: Python :: 3
Classifier: Programming Language :: Python :: 3.10
Classifier: Programming Language :: Python :: 3.11
Classifier: Programming Language :: Python :: 3.12
Classifier: Programming Language :: Python :: 3.13
Classifier: Topic :: Software Development :: Localization
Classifier: Topic :: Text Processing :: Linguistic
Requires-Python: >=3.10
Requires-Dist: lxml>=5.0.0
Requires-Dist: mcp>=1.0.0
Provides-Extra: dev
Requires-Dist: pytest-asyncio>=0.21.0; extra == 'dev'
Requires-Dist: pytest>=7.4.0; extra == 'dev'
